xmminiappcli/Notification.py
xmminiappcli/XMMiniAppEventHandler.py
xmminiappcli/XMMiniAppWatcher.py
xmminiappcli/__init__.py
xmminiappcli/utils.py
xmminiappcli-2.0.data/scripts/xmminiappcli
xmminiappcli-2.0.dist-info/METADATA
xmminiappcli-2.0.dist-info/WHEEL
xmminiappcli-2.0.dist-info/top_level.txt
xmminiappcli-2.0.dist-info/RECORD
