Metadata-Version: 2.1
Name: xmminiappcli
Version: 2.0
Summary: tools for ximalaya mini app
Home-page: UNKNOWN
Author: ocean.wang
Author-email: ocean.wang@ximalaya.com
License: MIT
Platform: UNKNOWN
Classifier: Programming Language :: Python :: 3
Classifier: License :: OSI Approved :: MIT License
Classifier: Operating System :: OS Independent
Requires-Dist: coloredlogs
Requires-Dist: fire
Requires-Dist: watchdog
